pyplz/__init__.py
pyplz/command.py
pyplz/console_utils.py
pyplz/error_handler.py
pyplz/exceptions.py
pyplz/main.py
pyplz/plz_app.py
pyplz/plz_parser.py
pyplz/task.py
pyplz/task_parser.py
pyplz/types.py
pyplz-0.12.2.dist-info/METADATA
pyplz-0.12.2.dist-info/WHEEL
pyplz-0.12.2.dist-info/entry_points.txt
pyplz-0.12.2.dist-info/top_level.txt
pyplz-0.12.2.dist-info/RECORD
