Metadata-Version: 2.4
Name: pyplz
Version: 0.12.2
Summary: A Python-first command runner
Project-URL: homepage, https://example.com
Project-URL: repository, https://github.com/yourusername/plz
Requires-Python: >=3.9
Requires-Dist: rich<14,>=13.9.4
Requires-Dist: python-dotenv<2,>=1.0.1
